{"http://fuzzy-sl.squirrel.link/ontology/activityDesc": ["set a representative point based on scientific papers using Google Maps"], "http://fuzzy-sl.squirrel.link/ontology/certaintyDesc": ["findspot mentioned in a scientific paper"], "http://fuzzy-sl.squirrel.link/ontology/certaintyLevel": ["fsl:medium"], "http://fuzzy-sl.squirrel.link/ontology/hasReference": ["Rosi et al., 1999"], "http://fuzzy-sl.squirrel.link/ontology/hasSource": ["fsl:PaperDesc"], "http://fuzzy-sl.squirrel.link/ontology/hasSourceType": ["fsl:Paper"], "http://rdfs.org/ns/void#inDataset": ["http://fuzzy-sl.squirrel.link/data/CI_LOD"], "http://www.w3.org/1999/02/22-rdf-syntax-ns#type": ["fsl:Georeferencing", "http://www.w3.org/ns/prov#Activity"], "http://www.w3.org/ns/prov#endedAtTime": ["2025-07-16T11:10:46.229230+00:00"], "http://www.w3.org/ns/prov#startedAtTime": ["2025-07-16T11:10:45.657460+00:00"], "http://www.w3.org/ns/prov#used": ["http://fuzzy-sl.squirrel.link/data/cisite_38"], "http://www.w3.org/ns/prov#wasAssociatedWith": ["http://orcid.org/0009-0008-2877-3204"]}